bleanser/__main__.py
bleanser/py.typed
bleanser/core/__init__.py
bleanser/core/__main__.py
bleanser/core/cli.py
bleanser/core/common.py
bleanser/core/compat.py
bleanser/core/main.py
bleanser/core/processor.py
bleanser/core/sqlite.py
bleanser/core/utils.py
bleanser/core/ext/dummy_executor.py
bleanser/core/ext/logging.py
bleanser/core/ext/sqlite_dumben.py
bleanser/core/modules/extract.py
bleanser/core/modules/json.py
bleanser/core/modules/sqlite.py
bleanser/core/modules/xml.py
bleanser/core/modules/tests/sqlite.py
bleanser/modules/antennapod_android.py
bleanser/modules/binary.py
bleanser/modules/bluemaestro.py
bleanser/modules/bumble_android.py
bleanser/modules/chrome.py
bleanser/modules/fbmessenger_android.py
bleanser/modules/firefox.py
bleanser/modules/foursquare.py
bleanser/modules/ghexport.py
bleanser/modules/goodreads.py
bleanser/modules/hinge_android.py
bleanser/modules/instagram_android.py
bleanser/modules/json_new.py
bleanser/modules/kobo.py
bleanser/modules/lastfm.py
bleanser/modules/monzo.py
bleanser/modules/pinboard.py
bleanser/modules/pocket.py
bleanser/modules/podcastaddict_android.py
bleanser/modules/reddit.py
bleanser/modules/rescuetime.py
bleanser/modules/rescuetime_android.py
bleanser/modules/skype_android.py
bleanser/modules/sleepasandroid_android.py
bleanser/modules/smscalls.py
bleanser/modules/spotify.py
bleanser/modules/spotifyexport.py
bleanser/modules/stackexchange.py
bleanser/modules/talon_android.py
bleanser/modules/tiktok_android.py
bleanser/modules/tinder_android.py
bleanser/modules/twitter_android.py
bleanser/modules/vk_android.py
bleanser/modules/whatsapp_android.py
bleanser/modules/xml_clean.py
bleanser/modules/hpi/fbmessenger_android.py
bleanser/modules/hpi/twitter_android.py
bleanser/modules/hpi/whatsapp_android.py
bleanser/tests/common.py
bleanser/tests/test_binary.py
bleanser/tests/test_hypothesis.py
bleanser-0.2.20251009.dist-info/METADATA
bleanser-0.2.20251009.dist-info/WHEEL
bleanser-0.2.20251009.dist-info/licenses/LICENSE
bleanser-0.2.20251009.dist-info/RECORD
