Metadata-Version: 2.4
Name: bleanser
Version: 0.2.20251009
Project-URL: Homepage, https://github.com/karlicoss/bleanser
Author-email: "Dima Gerasimov (@karlicoss)" <karlicoss@gmail.com>
Maintainer-email: "Dima Gerasimov (@karlicoss)" <karlicoss@gmail.com>
License: MIT License
License-File: LICENSE
Requires-Python: >=3.12
Requires-Dist: click
Requires-Dist: kompress
Requires-Dist: more-itertools
Requires-Dist: plumbum
Provides-Extra: extra
Requires-Dist: logzero; extra == 'extra'
Requires-Dist: python-magic; extra == 'extra'
Provides-Extra: hpi
Requires-Dist: hpi; extra == 'hpi'
Provides-Extra: json
Requires-Dist: orjson; extra == 'json'
Provides-Extra: xml
Requires-Dist: lxml; extra == 'xml'
Provides-Extra: zstd
Requires-Dist: kompress[zstd]; extra == 'zstd'
